funcchain/__init__.py
funcchain/py.typed
funcchain/backend/__init__.py
funcchain/backend/compiler.py
funcchain/backend/meta_inspect.py
funcchain/backend/prompt.py
funcchain/backend/settings.py
funcchain/backend/streaming.py
funcchain/model/__init__.py
funcchain/model/abilities.py
funcchain/model/defaults.py
funcchain/model/patches/__init__.py
funcchain/model/patches/llamacpp.py
funcchain/model/patches/ollama.py
funcchain/parser/__init__.py
funcchain/parser/custom.py
funcchain/parser/json_schema.py
funcchain/parser/openai_functions.py
funcchain/parser/primitive_types.py
funcchain/parser/schema_converter.py
funcchain/parser/selector.py
funcchain/schema/__init__.py
funcchain/schema/signature.py
funcchain/schema/types.py
funcchain/syntax/__init__.py
funcchain/syntax/decorators.py
funcchain/syntax/executable.py
funcchain/syntax/input_types.py
funcchain/syntax/output_types.py
funcchain/syntax/params.py
funcchain/syntax/components/__init__.py
funcchain/syntax/components/handler.py
funcchain/syntax/components/router.py
funcchain/utils/__init__.py
funcchain/utils/image.py
funcchain/utils/memory.py
funcchain/utils/msg_tools.py
funcchain/utils/pydantic.py
funcchain/utils/token_counter.py
funcchain-0.3.6.dist-info/METADATA
funcchain-0.3.6.dist-info/WHEEL
funcchain-0.3.6.dist-info/licenses/LICENSE
funcchain-0.3.6.dist-info/RECORD
