Metadata-Version: 2.3
Name: funcchain
Version: 0.3.6
Summary: 🔖 write prompts as python functions
Project-URL: Code, https://github.com/shroominic/funcchain
Project-URL: Documentation, https://shroominic.github.io/funcchain
Author-email: Shroominic <contact@shroominic.com>
License: MIT
Keywords: agent framework,ai,cognitive systems,funcchain,langchain,llm,pydantic,pythonic
Classifier: License :: OSI Approved :: MIT License
Classifier: Programming Language :: Python :: 3.10
Classifier: Programming Language :: Python :: 3.11
Classifier: Programming Language :: Python :: 3.12
Classifier: Topic :: Scientific/Engineering :: Artificial Intelligence
Requires-Python: <3.13,>=3.10
Requires-Dist: docstring-parser>=0.15
Requires-Dist: jinja2>=3
Requires-Dist: langchain-core>=0.2
Requires-Dist: langchain-openai>=0.1
Requires-Dist: pydantic-settings>=2
Provides-Extra: all
Requires-Dist: beautifulsoup4>=4.12; extra == 'all'
Requires-Dist: faiss-cpu>=1.7; extra == 'all'
Requires-Dist: huggingface-hub>=0.20; extra == 'all'
Requires-Dist: langchain-anthropic; extra == 'all'
Requires-Dist: langchain-community; extra == 'all'
Requires-Dist: langchain-google-genai; extra == 'all'
Requires-Dist: langchain-groq; extra == 'all'
Requires-Dist: langchain-openai; extra == 'all'
Requires-Dist: langchain>=0.1; extra == 'all'
Requires-Dist: llama-cpp-python>=0.2; extra == 'all'
Requires-Dist: pdf2image>=1.17; extra == 'all'
Requires-Dist: pdfminer>=20191125; extra == 'all'
Requires-Dist: pillow; extra == 'all'
Requires-Dist: unstructured>=0.12; extra == 'all'
Provides-Extra: anthropic
Requires-Dist: langchain-anthropic; extra == 'anthropic'
Provides-Extra: extras
Requires-Dist: beautifulsoup4>=4.12; extra == 'extras'
Requires-Dist: faiss-cpu>=1.7; extra == 'extras'
Requires-Dist: langchain>=0.1; extra == 'extras'
Requires-Dist: pdf2image>=1.17; extra == 'extras'
Requires-Dist: pdfminer>=20191125; extra == 'extras'
Requires-Dist: unstructured>=0.12; extra == 'extras'
Provides-Extra: google
Requires-Dist: langchain-google-genai; extra == 'google'
Provides-Extra: groq
Requires-Dist: langchain-groq; extra == 'groq'
Provides-Extra: image
Requires-Dist: pillow; extra == 'image'
Provides-Extra: llamacpp
Requires-Dist: huggingface-hub>=0.20; extra == 'llamacpp'
Requires-Dist: llama-cpp-python>=0.2; extra == 'llamacpp'
Provides-Extra: ollama
Requires-Dist: langchain-community; extra == 'ollama'
Provides-Extra: openai
Requires-Dist: langchain-openai; extra == 'openai'
